LICENSE
MANIFEST.in
README.md
setup.py
yandex_chain/ChatYandexGPT.py
yandex_chain/YandexGPT.py
yandex_chain/YandexGPTClassifier.py
yandex_chain/YandexGPTEmbeddings.py
yandex_chain/__init__.py
yandex_chain/util.py
yandex_chain.egg-info/PKG-INFO
yandex_chain.egg-info/SOURCES.txt
yandex_chain.egg-info/dependency_links.txt
yandex_chain.egg-info/requires.txt
yandex_chain.egg-info/top_level.txt