Metadata-Version: 2.1
Name: yandex-chain
Version: 0.0.9
Summary: Yandex GPT Support for LangChain
Home-page: https://github.com/yandex-datasphere/yandex-chain
Author: Dmitri Soshnikov
Author-email: dmitri@soshnikov.com
License: MIT license
Classifier: Programming Language :: Python :: 3
Classifier: Intended Audience :: Developers
Classifier: License :: OSI Approved :: MIT License
Classifier: Operating System :: OS Independent
Classifier: Topic :: Software Development
Classifier: Topic :: Software Development :: Libraries :: Python Modules
License-File: LICENSE
Requires-Dist: requests
Requires-Dist: langchain==0.2.1
Requires-Dist: tenacity
